LICENSE
README.md
setup.py
resimpy/Path.py
resimpy/__init__.py
resimpy/pcr/Amplify.py
resimpy/pcr/AmplifyTransloc.py
resimpy/pcr/Error.py
resimpy/pcr/ErrorTransloc.py
resimpy/pcr/__init__.py
resimpy/read/__init__.py
resimpy/read/barcode/Design.py
resimpy/read/barcode/__init__.py
resimpy/read/inf/Pseudo.py
resimpy/read/inf/__init__.py
resimpy/read/primer/Design.py
resimpy/read/primer/__init__.py
resimpy/read/seq/Design.py
resimpy/read/seq/RuleOut.py
resimpy/read/seq/__init__.py
resimpy/read/similarity/__init__.py
resimpy/read/similarity/distance/Hamming.py
resimpy/read/similarity/distance/__init__.py
resimpy/read/spacer/Design.py
resimpy/read/spacer/__init__.py
resimpy/read/umi/Design.py
resimpy/read/umi/Filter.py
resimpy/read/umi/Library.py
resimpy/read/umi/RuleOut.py
resimpy/read/umi/__init__.py
resimpy/sequencing/Calling.py
resimpy/sequencing/CallingTransloc.py
resimpy/sequencing/Error.py
resimpy/sequencing/ErrorTransloc.py
resimpy/sequencing/__init__.py
resimpy/simulate/__init__.py
resimpy/simulate/dispatcher/__init__.py
resimpy/simulate/dispatcher/batch/Bulk.py
resimpy/simulate/dispatcher/batch/CDNA.py
resimpy/simulate/dispatcher/batch/General.py
resimpy/simulate/dispatcher/batch/GeneralCondi.py
resimpy/simulate/dispatcher/batch/SingleCell.py
resimpy/simulate/dispatcher/batch/UMI.py
resimpy/simulate/dispatcher/batch/UMIDouble.py
resimpy/simulate/dispatcher/batch/__init__.py
resimpy/simulate/dispatcher/single/Bulk.py
resimpy/simulate/dispatcher/single/CDNA.py
resimpy/simulate/dispatcher/single/General.py
resimpy/simulate/dispatcher/single/GeneralCondi.py
resimpy/simulate/dispatcher/single/SingleCell.py
resimpy/simulate/dispatcher/single/UMI.py
resimpy/simulate/dispatcher/single/UMIDouble.py
resimpy/simulate/dispatcher/single/__init__.py
resimpy/simulate/initiator/Bulk.py
resimpy/simulate/initiator/CDNA.py
resimpy/simulate/initiator/General.py
resimpy/simulate/initiator/GeneralCondi.py
resimpy/simulate/initiator/SingleCell.py
resimpy/simulate/initiator/UMI.py
resimpyx.egg-info/PKG-INFO
resimpyx.egg-info/SOURCES.txt
resimpyx.egg-info/dependency_links.txt
resimpyx.egg-info/entry_points.txt
resimpyx.egg-info/requires.txt
resimpyx.egg-info/top_level.txt