Metadata-Version: 2.1
Name: resimpyx
Version: 0.0.2
Summary: REad SIMulation PY
Home-page: https://github.com/cribbslab; https://github.com/2003100127
Author: Jianfeng Sun
Author-email: jianfeng.sun@ndorms.ox.ac.uk
License: MIT
Keywords: pip,resimpy
Platform: any
Requires-Python: >3.6
License-File: LICENSE
